onaji/__init__.py
onaji/differ.py
onaji/logger.py
onaji-0.1.2.data/scripts/onajidiff
onaji-0.1.2.dist-info/DESCRIPTION.rst
onaji-0.1.2.dist-info/METADATA
onaji-0.1.2.dist-info/RECORD
onaji-0.1.2.dist-info/WHEEL
onaji-0.1.2.dist-info/entry_points.txt
onaji-0.1.2.dist-info/metadata.json
onaji-0.1.2.dist-info/top_level.txt
