Metadata-Version: 2.0
Name: onaji
Version: 0.1.2
Summary: A tool for creating regression tests through logging data during pytest runs.
Home-page: https://github.com/teamworksapp/onaji
Author: Jefferson Heard
Author-email: jheard@teamworks.com
License: MIT
Platform: UNKNOWN
Classifier: Framework :: Pytest
Classifier: Development Status :: 3 - Alpha
Classifier: Topic :: Software Development :: Build Tools
Classifier: Programming Language :: Python :: 3
Requires-Python: >=3
Requires-Dist: dulwich
